odoo/addons/account_asset_force_account/README.rst
odoo/addons/account_asset_force_account/__init__.py
odoo/addons/account_asset_force_account/__manifest__.py
odoo/addons/account_asset_force_account/i18n/account_asset_force_account.pot
odoo/addons/account_asset_force_account/i18n/ca_ES.po
odoo/addons/account_asset_force_account/i18n/es.po
odoo/addons/account_asset_force_account/i18n/it.po
odoo/addons/account_asset_force_account/models/__init__.py
odoo/addons/account_asset_force_account/models/account_asset.py
odoo/addons/account_asset_force_account/models/account_asset_line.py
odoo/addons/account_asset_force_account/models/account_move_line.py
odoo/addons/account_asset_force_account/readme/CONTRIBUTORS.md
odoo/addons/account_asset_force_account/readme/DESCRIPTION.md
odoo/addons/account_asset_force_account/readme/USAGE.md
odoo/addons/account_asset_force_account/static/description/icon.png
odoo/addons/account_asset_force_account/static/description/icon.svg
odoo/addons/account_asset_force_account/static/description/index.html
odoo/addons/account_asset_force_account/tests/__init__.py
odoo/addons/account_asset_force_account/tests/test_account_asset_management_force_account.py
odoo/addons/account_asset_force_account/views/account_asset.xml
odoo_addon_account_asset_force_account-18.0.1.0.0.3.dist-info/METADATA
odoo_addon_account_asset_force_account-18.0.1.0.0.3.dist-info/WHEEL
odoo_addon_account_asset_force_account-18.0.1.0.0.3.dist-info/top_level.txt
odoo_addon_account_asset_force_account-18.0.1.0.0.3.dist-info/RECORD
