Metadata-Version: 2.1
Name: odoo-addon-account_asset_force_account
Version: 18.0.1.0.0.3
Requires-Python: >=3.10
Requires-Dist: odoo-addon-account_asset_management==18.0.*
Requires-Dist: odoo==18.0.*
Summary: Asset Force Account
Home-page: https://github.com/OCA/account-financial-tools
License: AGPL-3
Author: Bernat Obrador (APSL-Nagarro), Odoo Community Association (OCA)
Author-email: support@odoo-community.org
Classifier: Programming Language :: Python
Classifier: Framework :: Odoo
Classifier: Framework :: Odoo :: 18.0
Classifier: License :: OSI Approved :: GNU Affero General Public License v3
